langchain_hive/__init__.py
langchain_hive/hive.py
langchain_hive-0.1.1.dist-info/METADATA
langchain_hive-0.1.1.dist-info/WHEEL
langchain_hive-0.1.1.dist-info/RECORD
