Metadata-Version: 2.3
Name: langchain-hive
Version: 0.1.1
Summary: Hive Intelligence tools
Requires-Python: >=3.9,<4.0
Classifier: Programming Language :: Python :: 3
Classifier: Programming Language :: Python :: 3.9
Classifier: Programming Language :: Python :: 3.10
Classifier: Programming Language :: Python :: 3.11
Classifier: Programming Language :: Python :: 3.12
Classifier: Programming Language :: Python :: 3.13
Requires-Dist: aiohttp (>=3.11.16,<4.0.0)
Requires-Dist: langchain-core (==0.3.49)
Requires-Dist: pydantic (>=2.11.2,<3.0.0)
Requires-Dist: requests (>=2.32.3,<3.0.0)
